eals/__init__.py
eals/eals.py
eals/serializer.py
eals/util.py
eals-0.9.6.dist-info/LICENSE
eals-0.9.6.dist-info/WHEEL
eals-0.9.6.dist-info/METADATA
eals-0.9.6.dist-info/RECORD
