Metadata-Version: 2.1
Name: eals
Version: 0.9.6
Summary: eALS - Element-wise Alternating Least Squares
Home-page: https://github.com/newspicks
Author: Akira Kitauchi
Author-email: kitauchi@gmail.com
Requires-Python: >=3.8,<3.11
Classifier: Programming Language :: Python :: 3
Classifier: Programming Language :: Python :: 3.8
Classifier: Programming Language :: Python :: 3.9
Classifier: Programming Language :: Python :: 3.10
Requires-Dist: joblib (>=1.2.0,<2.0.0)
Requires-Dist: numba (>=0.56.4,<0.57.0)
Requires-Dist: scipy (>=1.10.1,<2.0.0)
Project-URL: Repository, https://github.com/newspicks/eals
